[
    {
        "UpdateStageName": "Download LunaMP",
        "UpdateSourcePlatform": "All",
        "UpdateSource": "GithubRelease",
        "UpdateSourceData": "LunaMultiplayer-Server-linux-x64-Release.zip",
        "UpdateSourceArgs": "LunaMultiplayer/LunaMultiplayer",
        "UnzipUpdateSource": true,
        "OverwriteExistingFiles": false,
        "DeleteAfterExtract": true,
        "OneShot": false
    },
    {
        "UpdateStageName": "Install Dotnet",
        "UpdateSourcePlatform": "Linux",
        "UpdateSource": "FetchURL",
        "UpdateSourceData": "https://dot.net/v1/dotnet-install.sh",
        "UpdateSourceTarget": "{{$FullBaseDir}}",
        "UnzipUpdateSource": false,
        "OverwriteExistingFiles": false,
        "DeleteAfterExtract": false,
        "OneShot": true
    },
    {
        "UpdateStageName": "Set Dotnet Installer Exec Flag",
        "UpdateSourcePlatform": "Linux",
        "UpdateSource": "SetExecutableFlag",
        "UpdateSourceArgs": "{{$FullBaseDir}}dotnet-install.sh",
        "UnzipUpdateSource": false,
        "OverwriteExistingFiles": false,
        "DeleteAfterExtract": true,
        "OneShot": true
    },
    {
        "UpdateStageName": "Run Dotnet Installer",
        "UpdateSourcePlatform": "Linux",
        "UpdateSource": "Executable",
        "UpdateSourceData": "{{$FullBaseDir}}dotnet-install.sh",
        "UpdateSourceArgs": "--runtime dotnet --channel 6.0 --install-dir {{$FullBaseDir}}dotnet",
        "UnzipUpdateSource": false,
        "OverwriteExistingFiles": false,
        "DeleteAfterExtract": true,
        "OneShot": true
    },
    {
        "UpdateStageName": "Set LunaMP Server Exec Flag",
        "UpdateSourcePlatform": "Linux",
        "UpdateSource": "SetExecutableFlag",
        "UpdateSourceArgs": "{{$FullBaseDir}}LMPServer-linux-x64/Server",
        "UnzipUpdateSource": false,
        "OverwriteExistingFiles": false,
        "DeleteAfterExtract": true,
        "OneShot": true
    }
]
